shiinobi/__init__.py
shiinobi/builder/myanimelist/__init__.py
shiinobi/builder/myanimelist/anime.py
shiinobi/builder/myanimelist/anime_demographics.py
shiinobi/builder/myanimelist/anime_explicit_genres.py
shiinobi/builder/myanimelist/anime_genres.py
shiinobi/builder/myanimelist/anime_theme.py
shiinobi/builder/myanimelist/character.py
shiinobi/builder/myanimelist/staff.py
shiinobi/decorators/__init__.py
shiinobi/decorators/return_error_decorator.py
shiinobi/mixins/__init__.py
shiinobi/mixins/base.py
shiinobi/parser/myanimelist/__init__.py
shiinobi/parser/myanimelist/anime.py
shiinobi/parser/myanimelist/anime_character_and_staff_list.py
shiinobi/parser/myanimelist/anime_genre.py
shiinobi/parser/myanimelist/anime_producer.py
shiinobi/parser/myanimelist/character.py
shiinobi/parser/myanimelist/staff.py
shiinobi/utilities/__init__.py
shiinobi/utilities/regex.py
shiinobi/utilities/session.py
shiinobi/utilities/string.py
shiinobi-0.0.1.dist-info/LICENSE
shiinobi-0.0.1.dist-info/METADATA
shiinobi-0.0.1.dist-info/WHEEL
shiinobi-0.0.1.dist-info/RECORD
