Metadata-Version: 2.1
Name: shiinobi
Version: 0.0.1
Summary: 
License: MIT
Author: baseplate-admin
Author-email: 61817579+baseplate-admin@users.noreply.github.com
Requires-Python: >=3.9,<3.13
Classifier: License :: OSI Approved :: MIT License
Classifier: Programming Language :: Python :: 3
Classifier: Programming Language :: Python :: 3.9
Classifier: Programming Language :: Python :: 3.10
Classifier: Programming Language :: Python :: 3.11
Classifier: Programming Language :: Python :: 3.12
Requires-Dist: python-dateutil (>=2.9.0.post0,<3.0.0)
Requires-Dist: requests-cache (>=1.2.1,<2.0.0)
Requires-Dist: requests-ratelimiter (>=0.7.0,<0.8.0)
Requires-Dist: selectolax (>=0.3.21,<0.4.0)
